waterbend/__init__.py
waterbend-0.0.0.dist-info/METADATA
waterbend-0.0.0.dist-info/WHEEL
waterbend-0.0.0.dist-info/top_level.txt
waterbend-0.0.0.dist-info/RECORD
