Metadata-Version: 2.1
Name: waterbend
Version: 0.0.0
Summary: High-level Python library for DigitalOcean's REST API (v2)
Home-page: UNKNOWN
Author: Bulat Bochkariov
Author-email: bulat+pypi@bochkariov.com
License: UNKNOWN
Platform: UNKNOWN
Classifier: Programming Language :: Python :: 3 :: Only
Classifier: Development Status :: 1 - Planning
Classifier: License :: OSI Approved :: MIT License
Classifier: Operating System :: OS Independent
Classifier: Intended Audience :: Developers
Classifier: Topic :: Software Development :: Libraries
